pytest_xvfb.py
pytest_xvfb-3.0.0.dist-info/LICENSE
pytest_xvfb-3.0.0.dist-info/METADATA
pytest_xvfb-3.0.0.dist-info/WHEEL
pytest_xvfb-3.0.0.dist-info/entry_points.txt
pytest_xvfb-3.0.0.dist-info/top_level.txt
pytest_xvfb-3.0.0.dist-info/RECORD
