Metadata-Version: 2.1
Name: pytest-xvfb
Version: 3.0.0
Summary: A pytest plugin to run Xvfb (or Xephyr/Xvnc) for tests.
Author-email: Florian Bruhin <me@the-compiler.org>
Maintainer-email: Florian Bruhin <me@the-compiler.org>
License: MIT
Project-URL: Homepage, https://github.com/The-Compiler/pytest-xvfb
Classifier: Development Status :: 4 - Beta
Classifier: Intended Audience :: Developers
Classifier: Topic :: Software Development :: Testing
Classifier: Programming Language :: Python
Classifier: Programming Language :: Python :: 3 :: Only
Classifier: Programming Language :: Python :: 3
Classifier: Programming Language :: Python :: 3.7
Classifier: Programming Language :: Python :: 3.8
Classifier: Programming Language :: Python :: 3.9
Classifier: Programming Language :: Python :: 3.10
Classifier: Programming Language :: Python :: 3.11
Classifier: Programming Language :: Python :: Implementation :: CPython
Classifier: Programming Language :: Python :: Implementation :: PyPy
Classifier: Operating System :: OS Independent
Classifier: License :: OSI Approved :: MIT License
Requires-Python: >=3.7
License-File: LICENSE
